poker_calc/__init__.py
poker_calc/main.py
poker_calc/card/__init__.py
poker_calc/card/card.py
poker_calc/constants/__init__.py
poker_calc/constants/combos.py
poker_calc/constants/ranks.py
poker_calc/constants/suites.py
poker_calc/deck/__init__.py
poker_calc/deck/deck.py
poker_calc/interfaces/__init__.py
poker_calc/interfaces/argparser.py
poker_calc/interfaces/cli.py
poker_calc/player/__init__.py
poker_calc/player/player.py
poker_calc/pokergame/__init__.py
poker_calc/pokergame/pokergame.py
poker_calc/utils/__init__.py
poker_calc/utils/ranker.py
poker_calc-0.0.2.dist-info/LICENSE
poker_calc-0.0.2.dist-info/METADATA
poker_calc-0.0.2.dist-info/WHEEL
poker_calc-0.0.2.dist-info/entry_points.txt
poker_calc-0.0.2.dist-info/top_level.txt
poker_calc-0.0.2.dist-info/RECORD
