Metadata-Version: 2.1
Name: poker-calc
Version: 0.0.2
Summary: Poker Odds Calculator Calculate your hand odds against other players.
Author-email: Eduards Abishevs <eduards@abishevs.dev>
Project-URL: Homepage, https://github.com/Abishevs/poker_calc
Keywords: poker,poker odds calculator,Monte Carlo simulation
Classifier: Programming Language :: Python :: 3
Classifier: License :: OSI Approved :: MIT License
Classifier: Operating System :: OS Independent
Requires-Python: >=3.7
License-File: LICENSE
Requires-Dist: phevaluator ==0.5.2
